Metadata-Version: 2.1
Name: mlrun-pipelines-kfp-nop
Version: 0.1.4
Summary: MLRun Pipelines package to no-op any KFP functionality
Home-page: https://github.com/mlrun/mlrun
Author: Yaron Haviv
Author-email: yaronh@iguazio.com
License: Apache License 2.0
Keywords: mlrun,kfp
Requires-Python: >=3.9, <3.12
